pih/__init__.py
pih/console_api.py
pih/console_api_wrapper.py
pih/pih.py
pih/service_example.py
pih/widgets.py
pih/collections/__init__.py
pih/collections/service.py
pih/consts/__init__.py
pih/consts/ad.py
pih/consts/addresses.py
pih/consts/date_time.py
pih/consts/document.py
pih/consts/errors.py
pih/consts/events.py
pih/consts/facade.py
pih/consts/file.py
pih/consts/hosts.py
pih/consts/names.py
pih/consts/password.py
pih/consts/paths.py
pih/consts/polibase.py
pih/consts/recognize.py
pih/consts/rpc.py
pih/consts/service.py
pih/consts/service_commands.py
pih/consts/service_roles.py
pih/consts/settings.py
pih/consts/ssh_hosts.py
pih/rpc/__init__.py
pih/rpc/rpcCommandCall_pb2.py
pih/rpc/rpcCommandCall_pb2_grpc.py
pih/tools/__init__.py
pih/tools/service.py
pih-1.49933.dist-info/METADATA
pih-1.49933.dist-info/WHEEL
pih-1.49933.dist-info/top_level.txt
pih-1.49933.dist-info/RECORD
