Metadata-Version: 2.1
Name: pih
Version: 1.49933
Summary: PIH package
Home-page: https://pacifichosp.com/
Author: Nikita Karachentsev
Author-email: it@pacifichosp.com
License: MIT
Requires-Dist: ipih
